hoho2025/__init__.py
hoho2025/color_mappings.py
hoho2025/example_solutions.py
hoho2025/hoho.py
hoho2025/metric_helper.py
hoho2025/read_write_colmap.py
hoho2025/vis.py
hoho2025/viz3d.py
hoho2025-0.1.0.dist-info/licenses/LICENSE.txt
hoho2025-0.1.0.dist-info/METADATA
hoho2025-0.1.0.dist-info/WHEEL
hoho2025-0.1.0.dist-info/top_level.txt
hoho2025-0.1.0.dist-info/RECORD
